[{"sku":"7501384502294","description":"Kriadex","price":199.99,"tax":true,"weight":false,"items":1,"quantity":10},{"sku":"123456","description":"Netgear Router","price":199.99,"tax":true,"weight":false,"items":1,"quantity":9},{"sku":"7503002047637","description":"Ginkgo Biloba","price":99.99,"tax":true,"weight":false,"items":1,"quantity":6},{"sku":"083351767341","description":"Green Roads CBD OIL 550 MG ","price":499.99,"tax":true,"weight":false,"items":1,"quantity":3},{"sku":"075755602892","description":"Notebook","price":5.99,"tax":true,"weight":false,"items":1,"quantity":3},{"sku":"3","description":"Samsung S7","price":1200,"tax":true,"weight":false,"items":1,"quantity":1},{"sku":"4","description":"GameBoy Advance","price":149.99,"tax":true,"weight":false,"items":1,"quantity":3},{"sku":"19375939","description":"Samnsung S10","price":899.99,"tax":true,"weight":false,"items":1,"quantity":2},{"sku":"3805829","description":"Macbook Air","price":1000,"tax":true,"weight":false,"items":1,"quantity":2},{"sku":"4733839","description":"Macbook Pro","price":2000,"tax":true,"weight":false,"items":1,"quantity":3},{"sku":"92317334","description":"Drone","price":599.99,"tax":true,"weight":false,"items":1,"quantity":3},{"sku":"2491749","description":"Raspberry Pi 4","price":39.99,"tax":true,"weight":false,"items":1,"quantity":6},{"sku":"5757480","description":"Iphone 6","price":249.99,"tax":true,"weight":false,"items":1,"quantity":2},{"sku":"67890","description":"PS4 Controller","price":79.99,"tax":true,"weight":false,"items":1,"quantity":14},{"sku":"654321","description":"Switch","price":450.99,"tax":true,"weight":false,"items":1,"quantity":1},{"sku":"190","description":"Baby Yoda","price":9.99,"tax":true,"weight":false,"items":1,"quantity":1}]